canpeek/__init__.py
canpeek/__main__.py
canpeek/can_utils.py
canpeek/data_utils.py
canpeek/icons.qrc
canpeek/interfaces_utils.py
canpeek/models.py
canpeek/rc_icons.py
canpeek/co/__init__.py
canpeek/co/canopen_utils.py
canpeek/co/dcf2db.py
canpeek/co/nmt_editor.py
canpeek/co/sdo_client.py
canpeek/icons/canpeek.png
canpeek/icons/document-export.png
canpeek/icons/document-import.png
canpeek/icons/document-open-recent.png
canpeek/icons/document-save-as.png
canpeek-0.7.0.dist-info/METADATA
canpeek-0.7.0.dist-info/WHEEL
canpeek-0.7.0.dist-info/entry_points.txt
canpeek-0.7.0.dist-info/licenses/LICENSE
canpeek-0.7.0.dist-info/RECORD
