Metadata-Version: 2.4
Name: canpeek
Version: 0.7.0
Summary: A simple CAN bus monitoring tool, with dbc support.
Project-URL: Repository, https://github.com/denis-jullien/CANPeek
Project-URL: Releases, https://github.com/denis-jullien/CANPeek/releases/
License-File: LICENSE
Requires-Python: >=3.10
Requires-Dist: canopen
Requires-Dist: cantools>=40.2.3
Requires-Dist: dcf-tools>=2.4.2
Requires-Dist: docstring-parser>=0.16
Requires-Dist: pyside6-qtads>=4.4.0.1
Requires-Dist: pyside6>=6.9.1
Requires-Dist: python-can>=4.5.0
Requires-Dist: qasync>=0.27.1
Requires-Dist: qt-themes>=0.3.0
Provides-Extra: interfaces
Requires-Dist: canalystii>=0.1; extra == 'interfaces'
Requires-Dist: filelock>=3.18.0; extra == 'interfaces'
Requires-Dist: gs-usb>=0.3.0; extra == 'interfaces'
Requires-Dist: ics>=0.7.2; extra == 'interfaces'
Requires-Dist: nixnet>=0.3.2; extra == 'interfaces'
Requires-Dist: pyserial>=3.5; extra == 'interfaces'
Requires-Dist: uptime>=3.0.1; extra == 'interfaces'
Requires-Dist: usb>=0.0.83.dev0; extra == 'interfaces'
